CDNHTMLHelper/__about__.py
CDNHTMLHelper/__init__.py
cdnhtmlhelper-0.1.4b0.dist-info/METADATA
cdnhtmlhelper-0.1.4b0.dist-info/WHEEL
cdnhtmlhelper-0.1.4b0.dist-info/licenses/LICENSE
cdnhtmlhelper-0.1.4b0.dist-info/RECORD
