Metadata-Version: 2.1
Name: CDNHTMLHelper
Version: 0.1.4b0
Summary: Simplify adding external JavaScript and CSS files from jsDelivr CDN to web apps with Flask integration support.
Project-URL: Documentation, https://github.com/dbautz/cdnhtmlhelper#readme
Project-URL: Issues, https://github.com/dbautz/cdnhtmlhelper/issues
Project-URL: Source, https://github.com/dbautz/cdnhtmlhelper
Author-email: dbautz <dbautz@dbautz.com>
License-Expression: MIT
License-File: LICENSE
Classifier: Development Status :: 4 - Beta
Classifier: Programming Language :: Python
Classifier: Programming Language :: Python :: 3.7
Classifier: Programming Language :: Python :: 3.8
Classifier: Programming Language :: Python :: 3.9
Classifier: Programming Language :: Python :: 3.10
Classifier: Programming Language :: Python :: 3.11
Classifier: Programming Language :: Python :: Implementation :: CPython
Classifier: Programming Language :: Python :: Implementation :: PyPy
Requires-Python: >=3.7
Requires-Dist: markupsafe>=2.1.3
Requires-Dist: requests>=2.31.0
